LICENSE.txt
MANIFEST.in
README.txt
setup.py
bin/ssh-deploy-key
ssdk/__init__.py
ssdk/configuration.py
ssdk/status.py
ssh_deploy_key.egg-info/PKG-INFO
ssh_deploy_key.egg-info/SOURCES.txt
ssh_deploy_key.egg-info/dependency_links.txt
ssh_deploy_key.egg-info/requires.txt
ssh_deploy_key.egg-info/top_level.txt