Metadata-Version: 1.0
Name: ssh-deploy-key
Version: 0.3.0
Summary: Deploys your ssh key easily to a single remote host.  Deploys it rapidly to many remote hosts.
Home-page: https://grinder_to_graphite.readthedocs.org/en/latest/
Author: Travis Bear
Author-email: travis_bear@yahoo.com
License: LICENSE.txt
Keywords: ssh remote deploy key
Platform: UNKNOWN
